{"timestamp": "01-11-2023 17:17:35", "incumbents": [{"id": "ocd-person/bfdc2ee2-7760-4119-9d68-4962f1e1a285", "name": "Bert Stedman", "party": "Republican", "current_role": {"title": "Senator", "org_classification": "upper", "district": "R", "division_id": "ocd-division/country:us/state:ak/sldu:r"}, "jurisdiction": {"id": "ocd-jurisdiction/country:us/state:ak/government", "name": "Alaska", "classification": "state"}, "given_name": "Bert", "family_name": "Stedman", "image": "http://akleg.gov/images/legislators/smn.jpg", "email": "Senator.Bert.Stedman@akleg.gov", "gender": "", "birth_date": "", "death_date": "", "extras": {}, "created_at": "2018-10-18T14:32:52.200483+00:00", "updated_at": "2022-01-18T18:12:17.594179+00:00", "openstates_url": "https://openstates.org/person/bert-stedman-5q29p0nmv38qscr06wazcT/"}, {"id": "ocd-person/57554431-caac-4074-a8d8-40a4e6289ec1", "name": "Bill Wielechowski", "party": "Democratic", "current_role": {"title": "Senator", "org_classification": "upper", "district": "H", "division_id": "ocd-division/country:us/state:ak/sldu:h"}, "jurisdiction": {"id": "ocd-jurisdiction/country:us/state:ak/government", "name": "Alaska", "classification": "state"}, "given_name": "Bill", "family_name": "Wielechowski", "image": "http://akleg.gov/images/legislators/wie.jpg", "email": "Senator.Bill.Wielechowski@akleg.gov", "gender": "", "birth_date": "", "death_date": "", "extras": {}, "created_at": "2018-10-18T14:32:52.527012+00:00", "updated_at": "2022-01-18T18:12:17.093639+00:00", "openstates_url": "https://openstates.org/person/bill-wielechowski-2enIYUHMl8XWNTViDv5AcT/"}, {"id": "ocd-person/df5e57e6-9664-4a5b-ad78-b8537765a3ff", "name": "Click Bishop", "party": "Republican", "current_role": {"title": "Senator", "org_classification": "upper", "district": "C", "division_id": "ocd-division/country:us/state:ak/sldu:c"}, "jurisdiction": {"id": "ocd-jurisdiction/country:us/state:ak/government", "name": "Alaska", "classification": "state"}, "given_name": "Click", "family_name": "Bishop", "image": "http://akleg.gov/images/legislators/bis.jpg", "email": "Senator.Click.Bishop@akleg.gov", "gender": "", "birth_date": "", "death_date": "", "extras": {}, "created_at": "2018-10-18T14:33:02.413468+00:00", "updated_at": "2022-01-18T18:11:56.551534+00:00", "openstates_url": "https://openstates.org/person/click-bishop-6nUP2nnt7daAxD0SShjSql/"}, {"id": "ocd-person/d19f85d6-4018-49c7-9f3c-a477dd8096e6", "name": "David Wilson", "party": "Republican", "current_role": {"title": "Senator", "org_classification": "upper", "district": "D", "division_id": "ocd-division/country:us/state:ak/sldu:d"}, "jurisdiction": {"id": "ocd-jurisdiction/country:us/state:ak/government", "name": "Alaska", "classification": "state"}, "given_name": "David", "family_name": "Wilson", "image": "http://akleg.gov/images/legislators/wln.jpg", "email": "Senator.David.Wilson@akleg.gov", "gender": "", "birth_date": "", "death_date": "", "extras": {}, "created_at": "2018-10-18T14:33:02.836359+00:00", "updated_at": "2022-01-18T18:12:16.082568+00:00", "openstates_url": "https://openstates.org/person/david-wilson-6NYIVIH3fr3ev8qJsgjJUU/"}, {"id": "ocd-person/cd3ca264-553d-4e21-a993-e3f5097b1b77", "name": "Donald Olson", "party": "Democratic", "current_role": {"title": "Senator", "org_classification": "upper", "district": "T", "division_id": "ocd-division/country:us/state:ak/sldu:t"}, "jurisdiction": {"id": "ocd-jurisdiction/country:us/state:ak/government", "name": "Alaska", "classification": "state"}, "given_name": "Donald", "family_name": "Olson", "image": "http://akleg.gov/images/legislators/ols.jpg", "email": "Senator.Donald.Olson@akleg.gov", "gender": "", "birth_date": "", "death_date": "", "extras": {}, "created_at": "2018-10-18T14:32:59.609461+00:00", "updated_at": "2022-01-18T18:12:19.111875+00:00", "openstates_url": "https://openstates.org/person/donald-olson-6FH8Ue37yxIOa0rA1n2A1n/"}, {"id": "ocd-person/2ba2d14f-a08a-4f05-a9d4-5ca63d09561e", "name": "Elvi Gray-Jackson", "party": "Democratic", "current_role": {"title": "Senator", "org_classification": "upper", "district": "I", "division_id": "ocd-division/country:us/state:ak/sldu:i"}, "jurisdiction": {"id": "ocd-jurisdiction/country:us/state:ak/government", "name": "Alaska", "classification": "state"}, "given_name": "Elvi", "family_name": "Gray-Jackson", "image": "http://akleg.gov/images/legislators/gra.jpg", "email": "Senator.Elvi.Gray-Jackson@akleg.gov", "gender": "", "birth_date": "", "death_date": "", "extras": {}, "created_at": "2019-02-07T03:28:50.896208+00:00", "updated_at": "2022-01-18T18:11:57.558863+00:00", "openstates_url": "https://openstates.org/person/elvi-gray-jackson-1KL4pWpS9y7bxMNgcHDIf0/"}, {"id": "ocd-person/f5c83068-a809-4f57-8b77-1e77c87ee93b", "name": "Gary Stevens", "party": "Republican", "current_role": {"title": "Senator", "org_classification": "upper", "district": "P", "division_id": "ocd-division/country:us/state:ak/sldu:p"}, "jurisdiction": {"id": "ocd-jurisdiction/country:us/state:ak/government", "name": "Alaska", "classification": "state"}, "given_name": "Gary", "family_name": "Stevens", "image": "http://akleg.gov/images/legislators/stg.jpg", "email": "Senator.Gary.Stevens@akleg.gov", "gender": "", "birth_date": "", "death_date": "", "extras": {}, "created_at": "2018-10-18T14:33:08.505929+00:00", "updated_at": "2022-01-18T18:12:16.588651+00:00", "openstates_url": "https://openstates.org/person/gary-stevens-7TmbcTn42Eg38sHGYt7R9f/"}, {"id": "ocd-person/1ae3974e-660d-4526-b351-fff9b689b51a", "name": "Jesse Kiehl", "party": "Democratic", "current_role": {"title": "Senator", "org_classification": "upper", "district": "Q", "division_id": "ocd-division/country:us/state:ak/sldu:q"}, "jurisdiction": {"id": "ocd-jurisdiction/country:us/state:ak/government", "name": "Alaska", "classification": "state"}, "given_name": "Jesse", "family_name": "Kiehl", "image": "http://akleg.gov/images/legislators/kie.jpg", "email": "Senator.Jesse.Kiehl@akleg.gov", "gender": "", "birth_date": "", "death_date": "", "extras": {}, "created_at": "2019-02-07T03:28:08.873571+00:00", "updated_at": "2022-01-18T18:11:59.735067+00:00", "openstates_url": "https://openstates.org/person/jesse-kiehl-ojoDFHgKxr6aB2PLYDtak/"}, {"id": "ocd-person/e27ee042-a0cc-4aaa-8b1a-8a1685bc19df", "name": "Joshua Revak", "party": "Republican", "current_role": {"title": "Senator", "org_classification": "upper", "district": "M", "division_id": "ocd-division/country:us/state:ak/sldu:m"}, "jurisdiction": {"id": "ocd-jurisdiction/country:us/state:ak/government", "name": "Alaska", "classification": "state"}, "given_name": "Joshua", "family_name": "Revak", "image": "http://akleg.gov/images/legislators/rvk.jpg", "email": "Senator.Joshua.Revak@akleg.gov", "gender": "", "birth_date": "", "death_date": "", "extras": {}, "created_at": "2021-01-15T00:03:12.253352+00:00", "updated_at": "2022-01-18T18:12:08.923602+00:00", "openstates_url": "https://openstates.org/person/joshua-revak-6tOFOqpcq5rxYQPlhSFyRz/"}, {"id": "ocd-person/6b668254-46f3-4341-aadc-c8cbac0a6a0e", "name": "Lora Reinbold", "party": "Republican", "current_role": {"title": "Senator", "org_classification": "upper", "district": "G", "division_id": "ocd-division/country:us/state:ak/sldu:g"}, "jurisdiction": {"id": "ocd-jurisdiction/country:us/state:ak/government", "name": "Alaska", "classification": "state"}, "given_name": "Lora", "family_name": "Reinbold", "image": "http://akleg.gov/images/legislators/rei.jpg", "email": "Senator.Lora.Reinbold@akleg.gov", "gender": "", "birth_date": "", "death_date": "", "extras": {}, "created_at": "2018-10-18T14:32:59.307183+00:00", "updated_at": "2022-01-18T18:12:10.531498+00:00", "openstates_url": "https://openstates.org/person/lora-reinbold-3Gf1b5GKbUknIYVeoom74Q/"}, {"id": "ocd-person/e187d603-9202-4f64-80b0-6366702aec11", "name": "Lyman Hoffman", "party": "Democratic", "current_role": {"title": "Senator", "org_classification": "upper", "district": "S", "division_id": "ocd-division/country:us/state:ak/sldu:s"}, "jurisdiction": {"id": "ocd-jurisdiction/country:us/state:ak/government", "name": "Alaska", "classification": "state"}, "given_name": "Lyman", "family_name": "Hoffman", "image": "http://akleg.gov/images/legislators/hof.jpg", "email": "Senator.Lyman.Hoffman@akleg.gov", "gender": "", "birth_date": "", "death_date": "", "extras": {}, "created_at": "2018-10-18T14:33:01.825749+00:00", "updated_at": "2022-01-18T18:11:55.419055+00:00", "openstates_url": "https://openstates.org/person/lyman-hoffman-6rZLkRzbmUJTzk4YmFiuTR/"}, {"id": "ocd-person/aea19844-4572-4086-9462-e50ad3ff4b76", "name": "Mia Costello", "party": "Republican", "current_role": {"title": "Senator", "org_classification": "upper", "district": "K", "division_id": "ocd-division/country:us/state:ak/sldu:k"}, "jurisdiction": {"id": "ocd-jurisdiction/country:us/state:ak/government", "name": "Alaska", "classification": "state"}, "given_name": "Mia", "family_name": "Costello", "image": "http://akleg.gov/images/legislators/cos.jpg", "email": "Senator.Mia.Costello@akleg.gov", "gender": "", "birth_date": "", "death_date": "", "extras": {}, "created_at": "2018-10-18T14:33:08.199117+00:00", "updated_at": "2022-01-18T18:12:18.105759+00:00", "openstates_url": "https://openstates.org/person/mia-costello-5JWVrVyn6XUeD8PTRj3Lja/"}, {"id": "ocd-person/f8593ecf-bd23-47b9-92e4-ae6910979e00", "name": "Mike Shower", "party": "Republican", "current_role": {"title": "Senator", "org_classification": "upper", "district": "E", "division_id": "ocd-division/country:us/state:ak/sldu:e"}, "jurisdiction": {"id": "ocd-jurisdiction/country:us/state:ak/government", "name": "Alaska", "classification": "state"}, "given_name": "Mike", "family_name": "Shower", "image": "http://akleg.gov/images/legislators/sho.jpg", "email": "Senator.Mike.Shower@akleg.gov", "gender": "", "birth_date": "", "death_date": "", "extras": {}, "created_at": "2018-10-18T14:33:06.344610+00:00", "updated_at": "2022-01-18T18:12:14.232939+00:00", "openstates_url": "https://openstates.org/person/mike-shower-7Ycshh8JE94onsgXtzH8DI/"}, {"id": "ocd-person/6992b801-4fec-4f86-bc80-eff478ef36d8", "name": "Natasha von Imhof", "party": "Republican", "current_role": {"title": "Senator", "org_classification": "upper", "district": "L", "division_id": "ocd-division/country:us/state:ak/sldu:l"}, "jurisdiction": {"id": "ocd-jurisdiction/country:us/state:ak/government", "name": "Alaska", "classification": "state"}, "given_name": "Natasha", "family_name": "von Imhof", "image": "http://akleg.gov/images/legislators/von.jpg", "email": "Senator.Natasha.vonImhof@akleg.gov", "gender": "", "birth_date": "", "death_date": "", "extras": {}, "created_at": "2018-10-18T14:32:52.962801+00:00", "updated_at": "2022-01-18T18:12:11.071154+00:00", "openstates_url": "https://openstates.org/person/natasha-von-imhof-3DDFBm67Am1FhGJihEiHvc/"}, {"id": "ocd-person/f9961511-5a8f-4fb9-b34c-d045cdacfe5b", "name": "Peter Micciche", "party": "Republican", "current_role": {"title": "Senator", "org_classification": "upper", "district": "O", "division_id": "ocd-division/country:us/state:ak/sldu:o"}, "jurisdiction": {"id": "ocd-jurisdiction/country:us/state:ak/government", "name": "Alaska", "classification": "state"}, "given_name": "Peter", "family_name": "Micciche", "image": "http://akleg.gov/images/legislators/mhe.jpg", "email": "Senator.Peter.Micciche@akleg.gov", "gender": "", "birth_date": "", "death_date": "", "extras": {}, "created_at": "2018-10-18T14:33:00.613155+00:00", "updated_at": "2022-01-18T18:12:22.713988+00:00", "openstates_url": "https://openstates.org/person/peter-micciche-7axfzEeDM2rgG1M6amalmV/"}, {"id": "ocd-person/697cb834-6aa1-44f1-9c6e-9cf57ad30774", "name": "Robert Myers", "party": "Republican", "current_role": {"title": "Senator", "org_classification": "upper", "district": "B", "division_id": "ocd-division/country:us/state:ak/sldu:b"}, "jurisdiction": {"id": "ocd-jurisdiction/country:us/state:ak/government", "name": "Alaska", "classification": "state"}, "given_name": "Robert", "family_name": "Myers", "image": "http://akleg.gov/images/legislators/mye.jpg", "email": "Senator.Robert.Myers@akleg.gov", "gender": "", "birth_date": "", "death_date": "", "extras": {}, "created_at": "2021-12-16T18:37:57.058129+00:00", "updated_at": "2022-01-18T18:12:07.382904+00:00", "openstates_url": "https://openstates.org/person/robert-myers-3D3BrScWGqfEp8J54hiAiK/"}, {"id": "ocd-person/31f260ec-9346-4974-ad03-babf0b2af8f7", "name": "Roger Holland", "party": "Republican", "current_role": {"title": "Senator", "org_classification": "upper", "district": "N", "division_id": "ocd-division/country:us/state:ak/sldu:n"}, "jurisdiction": {"id": "ocd-jurisdiction/country:us/state:ak/government", "name": "Alaska", "classification": "state"}, "given_name": "Roger", "family_name": "Holland", "image": "http://akleg.gov/images/legislators/hld.jpg", "email": "Senator.Roger.Holland@akleg.gov", "gender": "", "birth_date": "", "death_date": "", "extras": {}, "created_at": "2021-01-15T00:03:13.286786+00:00", "updated_at": "2022-01-18T18:12:19.613957+00:00", "openstates_url": "https://openstates.org/person/roger-holland-1WFOGNFAjDqjLbHJSlRKeV/"}, {"id": "ocd-person/53f7b86b-ce31-4199-86ef-f566ae9aa02c", "name": "Scott Kawasaki", "party": "Democratic", "current_role": {"title": "Senator", "org_classification": "upper", "district": "A", "division_id": "ocd-division/country:us/state:ak/sldu:a"}, "jurisdiction": {"id": "ocd-jurisdiction/country:us/state:ak/government", "name": "Alaska", "classification": "state"}, "given_name": "Scott", "family_name": "Kawasaki", "image": "http://akleg.gov/images/legislators/kaw.jpg", "email": "Senator.Scott.Kawasaki@akleg.gov", "gender": "", "birth_date": "", "death_date": "", "extras": {}, "created_at": "2018-10-18T14:33:01.170732+00:00", "updated_at": "2022-01-18T18:11:58.618018+00:00", "openstates_url": "https://openstates.org/person/scott-kawasaki-2YRZRWadl6XKyFaSK5ac3g/"}, {"id": "ocd-person/f0e5bb6f-c8d1-43c1-a671-9c15d23781a1", "name": "Shelley Hughes", "party": "Republican", "current_role": {"title": "Senator", "org_classification": "upper", "district": "F", "division_id": "ocd-division/country:us/state:ak/sldu:f"}, "jurisdiction": {"id": "ocd-jurisdiction/country:us/state:ak/government", "name": "Alaska", "classification": "state"}, "given_name": "Shelley", "family_name": "Hughes", "image": "http://akleg.gov/images/legislators/hus.jpg", "email": "Senator.Shelley.Hughes@akleg.gov", "gender": "", "birth_date": "", "death_date": "", "extras": {}, "created_at": "2018-10-18T14:32:54.231182+00:00", "updated_at": "2022-01-18T18:12:14.987211+00:00", "openstates_url": "https://openstates.org/person/shelley-hughes-7KZ94f0m49ItJU9Jc4JrNJ/"}, {"id": "ocd-person/39f46457-d72f-41f9-9c60-ed28d3811c42", "name": "Tom Begich", "party": "Democratic", "current_role": {"title": "Senator", "org_classification": "upper", "district": "J", "division_id": "ocd-division/country:us/state:ak/sldu:j"}, "jurisdiction": {"id": "ocd-jurisdiction/country:us/state:ak/government", "name": "Alaska", "classification": "state"}, "given_name": "Tom", "family_name": "Begich", "image": "http://akleg.gov/images/legislators/bch.jpg", "email": "Senator.Tom.Begich@akleg.gov", "gender": "", "birth_date": "", "death_date": "", "extras": {}, "created_at": "2018-10-18T14:32:59.006807+00:00", "updated_at": "2022-01-18T18:12:04.584055+00:00", "openstates_url": "https://openstates.org/person/tom-begich-1lMFVIiq2hPVk6ISI4dIXq/"}]}